orm_json/__init__.py
orm_json/_jpy.py
orm_json/methods/__init__.py
orm_json/methods/custom.py
orm_json/methods/delete.py
orm_json/methods/insert.py
orm_json/methods/select.py
orm_json/methods/update.py
orm_json/utils/__init__.py
orm_json/utils/abstract.py
orm_json/utils/checking.py
orm_json/utils/enums.py
orm_json/utils/exception.py
orm_json/utils/models.py
orm_json/utils/output.py
orm_json-1.0.0.dist-info/LICENSE
orm_json-1.0.0.dist-info/METADATA
orm_json-1.0.0.dist-info/WHEEL
orm_json-1.0.0.dist-info/RECORD
